coveo_functools/__init__.py
coveo_functools/annotations.py
coveo_functools/casing.py
coveo_functools/dispatch.py
coveo_functools/exceptions.py
coveo_functools/finalizer.py
coveo_functools/flex/__init__.py
coveo_functools/flex/decorator.py
coveo_functools/flex/deserializer.py
coveo_functools/flex/factory_adapter.py
coveo_functools/flex/helpers.py
coveo_functools/flex/serializer.py
coveo_functools/flex/subclass_adapter.py
coveo_functools/flex/types.py
coveo_functools/py.typed
coveo_functools/wait.py
coveo_functools-3.0.dist-info/METADATA
coveo_functools-3.0.dist-info/WHEEL
coveo_functools-3.0.dist-info/RECORD
