Metadata-Version: 2.1
Name: coveo-functools
Version: 3.0
Summary: Generic function tooling helpers
Home-page: https://github.com/coveooss/coveo-python-oss/tree/main/coveo-functools
License: Apache-2.0
Author: Jonathan Piché
Author-email: tools@coveo.com
Requires-Python: >=3.9,<4
Classifier: License :: OSI Approved :: Apache Software License
Classifier: Programming Language :: Python :: 3
Classifier: Programming Language :: Python :: 3.9
Classifier: Programming Language :: Python :: 3.10
Classifier: Programming Language :: Python :: 3.11
Requires-Dist: inflection
Requires-Dist: typing_extensions
Project-URL: Repository, https://github.com/coveooss/coveo-python-oss/tree/main/coveo-functools
